{"nodes": [{"title": "Index.asp", "key": "D:\\Projetos\\demo.knockout.asp\\Index.asp", "items": [{"color": "purple", "name": "Id", "figure": "Decision", "iskey": true}]}, {"title": "ListarTarefas.asp", "key": "D:\\Projetos\\demo.knockout.asp\\ListarTarefas.asp", "items": [{"color": "purple", "name": "Id", "figure": "Decision", "iskey": true}]}, {"title": "ListarUsuario.asp", "key": "D:\\Projetos\\demo.knockout.asp\\ListarUsuario.asp", "items": [{"color": "purple", "name": "Id", "figure": "Decision", "iskey": true}]}, {"title": "ManterUsuario.asp", "key": "D:\\Projetos\\demo.knockout.asp\\ManterUsuario.asp", "items": [{"color": "purple", "name": "Id", "figure": "Decision", "iskey": true}]}, {"title": "BancoDeDados.asp", "key": "D:\\Projetos\\demo.knockout.asp\\Kadastro.Arquitetura\\BancoDeDados.asp", "items": [{"color": "purple", "name": "Id", "figure": "Decision", "iskey": true}]}, {"title": "EntityUtil.asp", "key": "D:\\Projetos\\demo.knockout.asp\\Kadastro.Comuns\\EntityUtil.asp", "items": [{"color": "purple", "name": "Id", "figure": "Decision", "iskey": true}]}, {"title": "SQLUtil.asp", "key": "D:\\Projetos\\demo.knockout.asp\\Kadastro.Comuns\\SQLUtil.asp", "items": [{"color": "purple", "name": "Id", "figure": "Decision", "iskey": true}, {"color": "purple", "name": "PrmSQL(prmValor, prmTipoSQL)", "figure": "Decision", "iskey": false}]}, {"title": "ValidationUtil.asp", "key": "D:\\Projetos\\demo.knockout.asp\\Kadastro.Comuns\\ValidationUtil.asp", "items": [{"color": "purple", "name": "Id", "figure": "Decision", "iskey": true}]}, {"title": "fnComparaData.asp", "key": "D:\\Projetos\\demo.knockout.asp\\Kadastro.Comuns\\Funcoes\\fnComparaData.asp", "items": [{"color": "purple", "name": "Id", "figure": "Decision", "iskey": true}, {"color": "purple", "name": "fnComparaData(data1, data2)", "figure": "Decision", "iskey": false}]}, {"title": "fnConverteDataSQL.asp", "key": "D:\\Projetos\\demo.knockout.asp\\Kadastro.Comuns\\Funcoes\\fnConverteDataSQL.asp", "items": [{"color": "purple", "name": "Id", "figure": "Decision", "iskey": true}, {"color": "purple", "name": "fnConverteDataSQL(prmData)", "figure": "Decision", "iskey": false}]}, {"title": "fnExecuteScalar.asp", "key": "D:\\Projetos\\demo.knockout.asp\\Kadastro.Comuns\\Funcoes\\fnExecuteScalar.asp", "items": [{"color": "purple", "name": "Id", "figure": "Decision", "iskey": true}, {"color": "purple", "name": "fnExecuteScalar(strRSSource, connSource)", "figure": "Decision", "iskey": false}]}, {"title": "fnValidaDataHora.asp", "key": "D:\\Projetos\\demo.knockout.asp\\Kadastro.Comuns\\Funcoes\\fnValidaDataHora.asp", "items": [{"color": "purple", "name": "Id", "figure": "Decision", "iskey": true}, {"color": "purple", "name": "fnValidaDataHora(strDatHor)", "figure": "Decision", "iskey": false}]}, {"title": "UsuarioDTO.asp", "key": "D:\\Projetos\\demo.knockout.asp\\Kadastro.Dominio\\UsuarioDTO.asp", "items": [{"color": "purple", "name": "Id", "figure": "Decision", "iskey": true}]}, {"title": "PontoRepository.asp", "key": "D:\\Projetos\\demo.knockout.asp\\Kadastro.Persistencia\\PontoRepository.asp", "items": [{"color": "purple", "name": "Id", "figure": "Decision", "iskey": true}, {"color": "purple", "name": "ObterPonto(prmId)", "figure": "Decision", "iskey": false}, {"color": "purple", "name": "ListarPonto(prmDia, prmMes, prmAno)", "figure": "Decision", "iskey": false}, {"color": "purple", "name": "SalvarPonto(prmid, prmdia, prmhoras)", "figure": "Decision", "iskey": false}, {"color": "purple", "name": "ObterIntervalo(prmId)", "figure": "Decision", "iskey": false}, {"color": "purple", "name": "ListarIntervalo(prmIdPonto, prmDia, prmMes, prmAno)", "figure": "Decision", "iskey": false}, {"color": "purple", "name": "SalvarIntervalo(prmid, prmidPonto, prmentrada, saida)", "figure": "Decision", "iskey": false}]}, {"title": "TipoUsuarioRepository.asp", "key": "D:\\Projetos\\demo.knockout.asp\\Kadastro.Persistencia\\TipoUsuarioRepository.asp", "items": [{"color": "purple", "name": "Id", "figure": "Decision", "iskey": true}]}, {"title": "UsuarioRepository.asp", "key": "D:\\Projetos\\demo.knockout.asp\\Kadastro.Persistencia\\UsuarioRepository.asp", "items": [{"color": "purple", "name": "Id", "figure": "Decision", "iskey": true}]}, {"title": "Cabecalho.asp", "key": "D:\\Projetos\\demo.knockout.asp\\Shared\\Cabecalho.asp", "items": [{"color": "purple", "name": "Id", "figure": "Decision", "iskey": true}]}, {"title": "Rodape.asp", "key": "D:\\Projetos\\demo.knockout.asp\\Shared\\Rodape.asp", "items": [{"color": "purple", "name": "Id", "figure": "Decision", "iskey": true}]}, {"title": "ScriptsComuns.asp", "key": "D:\\Projetos\\demo.knockout.asp\\Shared\\ScriptsComuns.asp", "items": [{"color": "purple", "name": "Id", "figure": "Decision", "iskey": true}]}], "links": [{"from": "D:\\Projetos\\demo.knockout.asp\\Index.asp", "text": "include", "to": "Cabecalho.asp", "toText": ">"}, {"from": "D:\\Projetos\\demo.knockout.asp\\Index.asp", "text": "include", "to": "ScriptsComuns.asp", "toText": ">"}, {"from": "D:\\Projetos\\demo.knockout.asp\\Index.asp", "text": "include", "to": "Rodape.asp", "toText": ">"}, {"from": "D:\\Projetos\\demo.knockout.asp\\ListarTarefas.asp", "text": "include", "to": "Cabecalho.asp", "toText": ">"}, {"from": "D:\\Projetos\\demo.knockout.asp\\ListarTarefas.asp", "text": "include", "to": "ScriptsComuns.asp", "toText": ">"}, {"from": "D:\\Projetos\\demo.knockout.asp\\ListarTarefas.asp", "text": "include", "to": "Rodape.asp", "toText": ">"}, {"from": "D:\\Projetos\\demo.knockout.asp\\ListarUsuario.asp", "text": "include", "to": "Cabecalho.asp", "toText": ">"}, {"from": "D:\\Projetos\\demo.knockout.asp\\ListarUsuario.asp", "text": "include", "to": "ScriptsComuns.asp", "toText": ">"}, {"from": "D:\\Projetos\\demo.knockout.asp\\ListarUsuario.asp", "text": "include", "to": "Rodape.asp", "toText": ">"}, {"from": "D:\\Projetos\\demo.knockout.asp\\ManterUsuario.asp", "text": "include", "to": "Cabecalho.asp", "toText": ">"}, {"from": "D:\\Projetos\\demo.knockout.asp\\ManterUsuario.asp", "text": "include", "to": "ScriptsComuns.asp", "toText": ">"}, {"from": "D:\\Projetos\\demo.knockout.asp\\ManterUsuario.asp", "text": "include", "to": "Rodape.asp", "toText": ">"}, {"from": "D:\\Projetos\\demo.knockout.asp\\Kadastro.Comuns\\SQLUtil.asp", "text": "include", "to": "fnConverteDataSQL.asp", "toText": ">"}, {"from": "D:\\Projetos\\demo.knockout.asp\\Kadastro.Comuns\\SQLUtil.asp", "text": "include", "to": "fnExecuteScalar.asp", "toText": ">"}, {"from": "D:\\Projetos\\demo.knockout.asp\\Kadastro.Comuns\\ValidationUtil.asp", "text": "include", "to": "fnComparaData.asp", "toText": ">"}, {"from": "D:\\Projetos\\demo.knockout.asp\\Kadastro.Comuns\\ValidationUtil.asp", "text": "include", "to": "fnValidaDataHora.asp", "toText": ">"}, {"from": "D:\\Projetos\\demo.knockout.asp\\Kadastro.Persistencia\\PontoRepository.asp", "text": "include", "to": "BancoDeDados.asp", "toText": ">"}, {"from": "D:\\Projetos\\demo.knockout.asp\\Kadastro.Persistencia\\PontoRepository.asp", "text": "include", "to": "SQLUtil.asp", "toText": ">"}, {"from": "D:\\Projetos\\demo.knockout.asp\\Kadastro.Persistencia\\UsuarioRepository.asp", "text": "include", "to": "BancoDeDados.asp", "toText": ">"}, {"from": "D:\\Projetos\\demo.knockout.asp\\Kadastro.Persistencia\\UsuarioRepository.asp", "text": "include", "to": "SQLUtil.asp", "toText": ">"}, {"from": "D:\\Projetos\\demo.knockout.asp\\Kadastro.Persistencia\\UsuarioRepository.asp", "text": "include", "to": "ValidationUtil.asp", "toText": ">"}, {"from": "D:\\Projetos\\demo.knockout.asp\\Shared\\Cabecalho.asp", "text": "link", "to": "Index.asp", "toText": ">"}, {"from": "D:\\Projetos\\demo.knockout.asp\\Shared\\Cabecalho.asp", "text": "link", "to": "ListarUsuario.asp", "toText": ">"}, {"from": "D:\\Projetos\\demo.knockout.asp\\Shared\\Cabecalho.asp", "text": "link", "to": "ManterUsuario.asp", "toText": ">"}, {"from": "D:\\Projetos\\demo.knockout.asp\\Shared\\Cabecalho.asp", "text": "link", "to": "ListarTarefas.asp", "toText": ">"}]}